{
  "products": [
    {
      "id": "2",
      "product_name": "Product2",
      "prix": "2000",
      "description": "Product 2 description",
      "stock": 30,
      "image": "image2.jpg"
    },
    {
      "id": "5751",
      "product_name": "test",
      "prix": "5000000",
      "description": "this is description of product 2",
      "stock": "250",
      "mark_product": "test",
      "image": "image1.png"
    },
    {
      "id": "882e",
      "product_name": "produit 3",
      "prix": "700",
      "description": "test",
      "stock": "0700",
      "mark_product": "7520",
      "image": "image"
    }
  ]
}